bruges/__init__.py
bruges/_version.py
bruges/bruges.py
bruges/get_bruges.py
bruges/attribute/__init__.py
bruges/attribute/complex.py
bruges/attribute/dipsteer.py
bruges/attribute/discontinuity.py
bruges/attribute/energy.py
bruges/attribute/horizon.py
bruges/attribute/spectraldecomp.py
bruges/attribute/spectrogram.py
bruges/filters/__init__.py
bruges/filters/anisodiff.py
bruges/filters/convolve.py
bruges/filters/filters.py
bruges/filters/kernels.py
bruges/filters/wavelets.py
bruges/models/__init__.py
bruges/models/panel.py
bruges/models/polarity.py
bruges/models/wedge.py
bruges/noise/__init__.py
bruges/noise/noise.py
bruges/petrophysics/__init__.py
bruges/petrophysics/petrophysics.py
bruges/reflection/__init__.py
bruges/reflection/reflection.py
bruges/rockphysics/__init__.py
bruges/rockphysics/anisotropy.py
bruges/rockphysics/bounds.py
bruges/rockphysics/elastic.py
bruges/rockphysics/fluids.py
bruges/rockphysics/fluidsub.py
bruges/rockphysics/moduli.py
bruges/rockphysics/rockphysicsmodels.py
bruges/rockphysics/rpm.py
bruges/rockphysics/rpt.py
bruges/transform/__init__.py
bruges/transform/coordinates.py
bruges/transform/cumavg.py
bruges/transform/nmo.py
bruges/transform/timedepthconv.py
bruges/unit/__init__.py
bruges/unit/unit.py
bruges/util/__init__.py
bruges/util/transformations.py
bruges/util/util.py
bruges-0.5.4.dist-info/AUTHORS.md
bruges-0.5.4.dist-info/LICENSE.txt
bruges-0.5.4.dist-info/METADATA
bruges-0.5.4.dist-info/WHEEL
bruges-0.5.4.dist-info/top_level.txt
bruges-0.5.4.dist-info/RECORD
