Metadata-Version: 2.1
Name: bruges
Version: 0.5.4
Summary: A library of geophysical equations.
Home-page: https://github.com/agilescientific/bruges
Author: The Bruges Authors
Author-email: hello@agilescientific.com
License: UNKNOWN
Platform: UNKNOWN
Classifier: Intended Audience :: Science/Research
Classifier: Development Status :: 4 - Beta
Classifier: Natural Language :: English
Classifier: Programming Language :: Python :: 3.6
Classifier: Programming Language :: Python :: 3.7
Classifier: Programming Language :: Python :: 3.8
Classifier: Programming Language :: Python :: 3.9
Classifier: Programming Language :: Python :: 3.10
Classifier: License :: OSI Approved :: Apache Software License
Classifier: Operating System :: OS Independent
Requires-Python: >=3.6
Provides-Extra: docs
Provides-Extra: test
Provides-Extra: dev
License-File: LICENSE.txt
License-File: AUTHORS.md
